ovos_transcription_validator/__init__.py
ovos_transcription_validator/version.py
ovos_transcription_validator/locale/ca-es/say_again.dialog
ovos_transcription_validator/locale/de-de/say_again.dialog
ovos_transcription_validator/locale/en-US/say_again.dialog
ovos_transcription_validator/locale/en-us/say_again.dialog
ovos_transcription_validator/locale/es-es/say_again.dialog
ovos_transcription_validator/locale/eu-es/say_again.dialog
ovos_transcription_validator/locale/fr-fr/say_again.dialog
ovos_transcription_validator/locale/gl-es/say_again.dialog
ovos_transcription_validator/locale/it-it/say_again.dialog
ovos_transcription_validator/locale/nl-nl/say_again.dialog
ovos_transcription_validator/locale/pt-br/say_again.dialog
ovos_transcription_validator/locale/pt-pt/say_again.dialog
ovos_transcription_validator_plugin-0.1.1a1.dist-info/licenses/LICENSE
ovos_transcription_validator_plugin-0.1.1a1.dist-info/METADATA
ovos_transcription_validator_plugin-0.1.1a1.dist-info/WHEEL
ovos_transcription_validator_plugin-0.1.1a1.dist-info/entry_points.txt
ovos_transcription_validator_plugin-0.1.1a1.dist-info/top_level.txt
ovos_transcription_validator_plugin-0.1.1a1.dist-info/zip-safe
ovos_transcription_validator_plugin-0.1.1a1.dist-info/RECORD
