Metadata-Version: 2.4
Name: ovos-transcription-validator-plugin
Version: 0.1.1a1
Summary: OpenVoiceOS Transcription Validator Plugin
Home-page: https://github.com/TigreGotico/ovos-transcription-validator-plugin
Author: TigreGotico
Author-email: jarbasai@mailfence.com
License: apache-2.0
Classifier: Development Status :: 3 - Alpha
Classifier: Intended Audience :: Developers
Classifier: Topic :: Text Processing :: Linguistic
Classifier: License :: OSI Approved :: Apache Software License
License-File: LICENSE
Requires-Dist: ovos-utils>=0.6.0
Requires-Dist: ovos-plugin-manager
Requires-Dist: requests
Dynamic: author
Dynamic: author-email
Dynamic: classifier
Dynamic: description
Dynamic: description-content-type
Dynamic: home-page
Dynamic: license
Dynamic: license-file
Dynamic: requires-dist
Dynamic: summary
